generator/README.md
generator/__init__.py
generator/names.txt
generator/text.txt
generator/var_generator.py
generator/var_object.py
generator/var_parser.py
crczp_automated_problem_generation_lib-1.0.2.dist-info/METADATA
crczp_automated_problem_generation_lib-1.0.2.dist-info/WHEEL
crczp_automated_problem_generation_lib-1.0.2.dist-info/licenses/LICENSE
crczp_automated_problem_generation_lib-1.0.2.dist-info/RECORD
