Metadata-Version: 2.4
Name: crczp-automated-problem-generation-lib
Version: 1.0.2
Summary: Random generator of selected variables
Author-email: Daniel Kosc <485652@mail.muni.cz>
License-Expression: MIT
License-File: LICENSE
Requires-Python: >=3.9
Requires-Dist: better-profanity==0.6.1
Requires-Dist: pyyaml>=6.0.2
